questpy_test/__init__.py
questpy_test/main.py
questpy_test/es_gui/__init__.py
questpy_test/es_gui/settings.py
questpy_test/es_gui/apps/__init__.py
questpy_test/es_gui/apps/btm/__init__.py
questpy_test/es_gui/apps/btm/cost_savings.py
questpy_test/es_gui/apps/btm/home.py
questpy_test/es_gui/apps/btm/op_handler.py
questpy_test/es_gui/apps/btm/reporting.py
questpy_test/es_gui/apps/btm/results_viewer.py
questpy_test/es_gui/apps/performance/__init__.py
questpy_test/es_gui/apps/performance/home.py
questpy_test/es_gui/apps/performance/performance_sim.py
questpy_test/es_gui/apps/performance/performance_sim_handler.py
questpy_test/es_gui/apps/performance/results_viewer.py
questpy_test/es_gui/apps/tech_selection/__init__.py
questpy_test/es_gui/apps/tech_selection/analysis.py
questpy_test/es_gui/apps/tech_selection/fAux.py
questpy_test/es_gui/apps/tech_selection/fFeasibility.py
questpy_test/es_gui/apps/tech_selection/fPlots.py
questpy_test/es_gui/apps/tech_selection/home.py
questpy_test/es_gui/apps/tech_selection/results_viewer.py
questpy_test/es_gui/apps/tech_selection/tech_selection_wizard.py
questpy_test/es_gui/apps/valuation/__init__.py
questpy_test/es_gui/apps/valuation/batchrunscreen.py
questpy_test/es_gui/apps/valuation/home.py
questpy_test/es_gui/apps/valuation/loaddatascreen.py
questpy_test/es_gui/apps/valuation/op_handler.py
questpy_test/es_gui/apps/valuation/reporting.py
questpy_test/es_gui/apps/valuation/results_viewer.py
questpy_test/es_gui/apps/valuation/setparametersscreen.py
questpy_test/es_gui/apps/valuation/valuationscreen.py
questpy_test/es_gui/apps/valuation/wizard.py
questpy_test/es_gui/proving_grounds/ChartTestApp.py
questpy_test/es_gui/proving_grounds/__init__.py
questpy_test/es_gui/proving_grounds/charts.py
questpy_test/es_gui/proving_grounds/data_importer.py
questpy_test/es_gui/proving_grounds/data_importer_test_app.py
questpy_test/es_gui/proving_grounds/help_carousel.py
questpy_test/es_gui/proving_grounds/help_carousel_test_app.py
questpy_test-1.6.dist-info/LICENSE
questpy_test-1.6.dist-info/METADATA
questpy_test-1.6.dist-info/WHEEL
questpy_test-1.6.dist-info/top_level.txt
questpy_test-1.6.dist-info/RECORD
